classifierPratik/__init__.py
classifierPratik/classifierPratikFunctions.py
tests/__init__.py
tests/test_classifier.py
classifierpratik-0.0.4.dist-info/METADATA
classifierpratik-0.0.4.dist-info/WHEEL
classifierpratik-0.0.4.dist-info/top_level.txt
classifierpratik-0.0.4.dist-info/RECORD
